setup.cfg
setup.py
pylibtracer/__init__.py
pylibtracer/libtracer.py
pylibtracer/utils.py
pylibtracer.egg-info/PKG-INFO
pylibtracer.egg-info/SOURCES.txt
pylibtracer.egg-info/dependency_links.txt
pylibtracer.egg-info/entry_points.txt
pylibtracer.egg-info/not-zip-safe
pylibtracer.egg-info/top_level.txt