Metadata-Version: 1.0
Name: pylibtracer
Version: 0.9.1
Summary: pylibtracer is a Python library used to find Python modules you are using in a project.
Home-page: http://opensource.ollix.com/pylibtracer
Author: Olli Wang
Author-email: olliwang@ollix.com
License: MIT
Platform: UNKNOWN
Classifier: Intended Audience :: Developers
Classifier: License :: OSI Approved
Classifier: Operating System :: OS Independent
Classifier: Programming Language :: Python
Classifier: Topic :: Utilities
